barrins_codex/__init__.py
barrins_codex/card_list.py
barrins_codex/config.py
barrins_codex/moxfield_decklist.py
barrins_codex/navigation.py
barrins_codex/static/robots.txt
barrins_codex/static/css/dropdown_menu.css
barrins_codex/static/img/banner.jpg
barrins_codex/static/img/codex.jpg
barrins_codex/static/img/favicon.ico
barrins_codex/static/img/icons/codex.svg
barrins_codex/static/img/icons/discord.png
barrins_codex/static/img/icons/twitch.png
barrins_codex/static/img/icons/twitter.png
barrins_codex/static/img/matchs/adeliz-vs-kinnan.jpg
barrins_codex/static/img/matchs/aminatou-vs-beamtown.jpg
barrins_codex/static/img/matchs/aminatou-vs-klothys.jpg
barrins_codex/static/img/matchs/aminatou-vs-tiamat.jpg
barrins_codex/static/img/matchs/azusa-vs-elmarhargilde.jpg
barrins_codex/static/img/matchs/bjornawernog-vs-grist.jpg
barrins_codex/static/img/matchs/cecilywernog-vs-kroxa.jpg
barrins_codex/static/img/matchs/dennick-vs-hinata.jpg
barrins_codex/static/img/matchs/doran-vs-marchesa.jpg
barrins_codex/static/img/matchs/elmarsophina-vs-shorikai.jpg
barrins_codex/static/img/matchs/elminster-vs-wilson-simic.jpg
barrins_codex/static/img/matchs/erinis-selesnya-vs-raff.jpg
barrins_codex/static/img/matchs/esika-vs-niv-5c.jpg
barrins_codex/static/img/matchs/ghyrson-vs-nivmizzet.jpg
barrins_codex/static/img/matchs/grenzo-vs-shanna.jpg
barrins_codex/static/img/matchs/grist-vs-minscboo.jpg
barrins_codex/static/img/matchs/grist-vs-raffine.jpg
barrins_codex/static/img/matchs/grist-vs-sythis.jpg
barrins_codex/static/img/matchs/gut-boros-vs-yoshimaru-boros.jpg
barrins_codex/static/img/matchs/hogaak-vs-minscboo.jpg
barrins_codex/static/img/matchs/isamaru-vs-gitrog.jpg
barrins_codex/static/img/matchs/jori-en-vs-maelstrom-wanderer.jpg
barrins_codex/static/img/matchs/jori-en-vs-sygg.jpg
barrins_codex/static/img/matchs/juri-vs-sai.jpg
barrins_codex/static/img/matchs/juri-vs-wilson-simic.jpg
barrins_codex/static/img/matchs/kari-zev-vs-killian-budget.jpg
barrins_codex-9.6.0.dist-info/LICENSE
barrins_codex-9.6.0.dist-info/METADATA
barrins_codex-9.6.0.dist-info/WHEEL
barrins_codex-9.6.0.dist-info/entry_points.txt
barrins_codex-9.6.0.dist-info/top_level.txt
barrins_codex-9.6.0.dist-info/zip-safe
barrins_codex-9.6.0.dist-info/RECORD
